{
    "Ar36": {
        "error": 0.5959139182969632,
        "error_type": "SEM",
        "filter_outliers_dict": {
            "filter_outliers": true,
            "iterations": 1,
            "std_devs": 2
        },
        "fit": "linear",
        "value": 38.17172145311353
    },
    "Ar37": {
        "error": 2.495100867332887e-07,
        "error_type": "SEM",
        "filter_outliers_dict": {
            "filter_outliers": true,
            "iterations": 1,
            "std_devs": 2
        },
        "fit": "linear",
        "value": 5.814736244080819e-06
    },
    "Ar38": {
        "error": 2.7133364288051966e-07,
        "error_type": "SEM",
        "filter_outliers_dict": {
            "filter_outliers": true,
            "iterations": 1,
            "std_devs": 2
        },
        "fit": "linear",
        "value": 1.2417284248374463e-06
    },
    "Ar39": {
        "error": 1.7690853925945973e-07,
        "error_type": "SEM",
        "filter_outliers_dict": {
            "filter_outliers": true,
            "iterations": 1,
            "std_devs": 2
        },
        "fit": "linear",
        "value": -6.997099197970996e-06
    },
    "Ar40": {
        "error": 1.746311019945782e-06,
        "error_type": "SEM",
        "filter_outliers_dict": {
            "filter_outliers": true,
            "iterations": 1,
            "std_devs": 2
        },
        "fit": "linear",
        "value": 8.08331646884043e-05
    }
}