{
    "Ar36": {
        "error": 1.5983748951423566,
        "error_type": "SEM",
        "filter_outliers_dict": {
            "filter_outliers": true,
            "iterations": 1,
            "std_devs": 2
        },
        "fit": "linear",
        "value": 173.41901435227493
    },
    "Ar37": {
        "error": 2.458671058574822e-07,
        "error_type": "SEM",
        "filter_outliers_dict": {
            "filter_outliers": true,
            "iterations": 1,
            "std_devs": 2
        },
        "fit": "linear",
        "value": 5.6598240983156294e-06
    },
    "Ar38": {
        "error": 3.105392395658522e-07,
        "error_type": "SEM",
        "filter_outliers_dict": {
            "filter_outliers": true,
            "iterations": 1,
            "std_devs": 2
        },
        "fit": "linear",
        "value": 1.3703945887194758e-06
    },
    "Ar39": {
        "error": 2.119738650988978e-07,
        "error_type": "SEM",
        "filter_outliers_dict": {
            "filter_outliers": true,
            "iterations": 1,
            "std_devs": 2
        },
        "fit": "linear",
        "value": -6.919841759287482e-06
    },
    "Ar40": {
        "error": 4.0252713128557205e-06,
        "error_type": "SEM",
        "filter_outliers_dict": {
            "filter_outliers": true,
            "iterations": 1,
            "std_devs": 2
        },
        "fit": "linear",
        "value": 0.0008329307758674427
    }
}