{
    "Ar36": {
        "error": 0.8145338219092945,
        "error_type": "SEM",
        "filter_outliers_dict": {
            "filter_outliers": true,
            "iterations": 1,
            "std_devs": 2
        },
        "fit": "linear",
        "value": 55.605618563498915
    },
    "Ar37": {
        "error": 2.179969652454178e-07,
        "error_type": "SEM",
        "filter_outliers_dict": {
            "filter_outliers": true,
            "iterations": 1,
            "std_devs": 2
        },
        "fit": "linear",
        "value": 7.755782047209892e-06
    },
    "Ar38": {
        "error": 3.203716568155837e-07,
        "error_type": "SEM",
        "filter_outliers_dict": {
            "filter_outliers": true,
            "iterations": 1,
            "std_devs": 2
        },
        "fit": "linear",
        "value": 5.926014827835755e-07
    },
    "Ar39": {
        "error": 1.7699900157997957e-07,
        "error_type": "SEM",
        "filter_outliers_dict": {
            "filter_outliers": true,
            "iterations": 1,
            "std_devs": 2
        },
        "fit": "linear",
        "value": -5.140518515736075e-06
    },
    "Ar40": {
        "error": 1.7455012653505877e-06,
        "error_type": "SEM",
        "filter_outliers_dict": {
            "filter_outliers": true,
            "iterations": 1,
            "std_devs": 2
        },
        "fit": "linear",
        "value": 8.478634180104452e-05
    }
}