{
    "Ar36": {
        "error": 1.8090087728847977,
        "error_type": "SEM",
        "filter_outliers_dict": {
            "filter_outliers": true,
            "iterations": 1,
            "std_devs": 2
        },
        "fit": "linear",
        "value": 395.81129334475884
    },
    "Ar37": {
        "error": 2.8933163032069805e-07,
        "error_type": "SEM",
        "filter_outliers_dict": {
            "filter_outliers": true,
            "iterations": 1,
            "std_devs": 2
        },
        "fit": "linear",
        "value": 5.409383304992062e-06
    },
    "Ar38": {
        "error": 3.675561520696676e-07,
        "error_type": "SEM",
        "filter_outliers_dict": {
            "filter_outliers": true,
            "iterations": 1,
            "std_devs": 2
        },
        "fit": "linear",
        "value": 2.215013616685854e-06
    },
    "Ar39": {
        "error": 2.2831815490872953e-07,
        "error_type": "SEM",
        "filter_outliers_dict": {
            "filter_outliers": true,
            "iterations": 1,
            "std_devs": 2
        },
        "fit": "linear",
        "value": -5.490899842549248e-06
    },
    "Ar40": {
        "error": 1.8558165786621592e-06,
        "error_type": "SEM",
        "filter_outliers_dict": {
            "filter_outliers": true,
            "iterations": 1,
            "std_devs": 2
        },
        "fit": "linear",
        "value": 0.002028313036023836
    }
}